registers/registers.v

module registers (
    input  clock,
    input  we,
    input  [4:0] reg_to_write_addr,
    input  [4:0] reg_stored_1_addr,
    input  [4:0] reg_stored_2_addr,
    input  [31:0] reg_to_write_data,
    output [31:0] reg_stored_1_data,
    output [31:0] reg_stored_2_data
);

    // 32 regs with  32bit width each one
    logic [31:0] regs [0:31];
   
    // Read ports for reg_stored_1 and reg_stored_2
    assign reg_stored_1_data = regs[reg_stored_1_addr];
    assign reg_stored_2_data = regs[reg_stored_2_addr];

    // Register x0 is always 0
    initial regs[0] = 32'b0;

    // Write port for reg_to_write
    always @(posedge clock)
        if (we && (reg_to_write_addr != 5'b0)) 
		regs[reg_to_write_addr] <= reg_to_write_data;

  // Dump waves
  initial begin
    $dumpfile("registers.vcd");
    $dumpvars(0, registers);
    #1;
  end

endmodule

registers/registers.vcd
$date
	Mon Nov 11 17:18:58 2024
$end
$version
	Icarus Verilog
$end
$timescale
	1ps
$end
$scope module registers $end
$var wire 1 ! clock $end
$var wire 5 " reg_stored_1_addr [4:0] $end
$var wire 32 # reg_stored_1_data [31:0] $end
$var wire 5 $ reg_stored_2_addr [4:0] $end
$var wire 32 % reg_stored_2_data [31:0] $end
$var wire 5 & reg_to_write_addr [4:0] $end
$var wire 32 ' reg_to_write_data [31:0] $end
$var wire 1 ( we $end
$upscope $end
$enddefinitions $end
$comment Show the parameter values. $end
$dumpall
$end
#0
$dumpvars
0(
b101 '
b10100 &
b0 %
b0 $
b0 #
b0 "
1!
$end
#500
0!
#1000
1!
#1500
0!
#2000
1!
1(
#2500
0!
#3000
1!
#3500
0!
#4000
1!
0(
#4500
0!
#5000
1!
#5500
0!
#6000
1!
b10010 '
b10110 &
#6500
0!
#7000
1!
#7500
0!
#8000
1!
1(
#8500
0!
#9000
1!
#9500
0!
#10000
1!
0(
#10500
0!
#11000
1!
#11500
0!
#12000
1!
#12500
0!
#13000
1!
#13500
0!
#14000
1!
#14500
0!
#15000
1!
#15500
0!
#16000
1!
#16500
0!
#17000
1!
#17500
0!
#18000
1!
#18500
0!
#19000
1!
#19500
0!
#20000
b101 #
1!
b10100 "
#20500
0!
#21000
1!
#21500
0!
#22000
1!
#22500
0!
#23000
1!
#23500
0!
#24000
1!
#24500
0!
#25000
1!
#25500
0!
#26000
1!
#26500
0!
#27000
1!
#27500
0!
#28000
1!
#28500
0!
#29000
1!
#29500
0!
#30000
b10010 %
1!
b10110 $
